pychat/__init__.py
pychat/__main__.py
pychat/client.py
pychat/server.py
pytermichat-1.1.0.dist-info/LICENSE
pytermichat-1.1.0.dist-info/METADATA
pytermichat-1.1.0.dist-info/WHEEL
pytermichat-1.1.0.dist-info/top_level.txt
pytermichat-1.1.0.dist-info/RECORD
