Metadata-Version: 2.1
Name: pytermichat
Version: 1.1.0
Summary: Python powered chat in terminal
Home-page: https://github.com/termichat/py
Author: Mineinjava
Author-email: mineinjava@minein.me
License: GPLv3
Project-URL: Bug Tracker, https://github.com/pypa/sampleproject/issues
Project-URL: Source, https://github.com/termichat/py
Platform: UNKNOWN
Classifier: Programming Language :: Python :: 3
Classifier: Operating System :: OS Independent
Requires-Python: >=3.7
